cve_sentinel/__init__.py
cve_sentinel/__main__.py
cve_sentinel/cli.py
cve_sentinel/config.py
cve_sentinel/matcher.py
cve_sentinel/matcher_combined.py
cve_sentinel/reporter.py
cve_sentinel/scanner.py
cve_sentinel/analyzers/__init__.py
cve_sentinel/analyzers/base.py
cve_sentinel/analyzers/go.py
cve_sentinel/analyzers/maven.py
cve_sentinel/analyzers/npm.py
cve_sentinel/analyzers/php.py
cve_sentinel/analyzers/python.py
cve_sentinel/analyzers/ruby.py
cve_sentinel/analyzers/rust.py
cve_sentinel/fetchers/__init__.py
cve_sentinel/fetchers/nvd.py
cve_sentinel/fetchers/nvd_package_matcher.py
cve_sentinel/fetchers/osv.py
cve_sentinel/scanners/__init__.py
cve_sentinel/scanners/import_scanner.py
cve_sentinel/utils/__init__.py
cve_sentinel/utils/cache.py
cve_sentinel-0.2.0.dist-info/METADATA
cve_sentinel-0.2.0.dist-info/WHEEL
cve_sentinel-0.2.0.dist-info/entry_points.txt
cve_sentinel-0.2.0.dist-info/licenses/LICENSE
cve_sentinel-0.2.0.dist-info/RECORD
