Metadata-Version: 2.4
Name: cve-sentinel
Version: 0.2.0
Summary: CVE auto-detection and remediation proposal system for Claude Code
Project-URL: Homepage, https://github.com/cawa102/cveSentinel
Project-URL: Documentation, https://github.com/cawa102/cveSentinel#readme
Project-URL: Repository, https://github.com/cawa102/cveSentinel
Project-URL: Issues, https://github.com/cawa102/cveSentinel/issues
Author: CVE Sentinel Team
License-Expression: MIT
License-File: LICENSE
Keywords: claude-code,cve,scanner,security,vulnerability
Classifier: Development Status :: 3 - Alpha
Classifier: Intended Audience :: Developers
Classifier: License :: OSI Approved :: MIT License
Classifier: Programming Language :: Python :: 3
Classifier: Programming Language :: Python :: 3.9
Classifier: Programming Language :: Python :: 3.10
Classifier: Programming Language :: Python :: 3.11
Classifier: Programming Language :: Python :: 3.12
Classifier: Topic :: Security
Requires-Python: >=3.9
Requires-Dist: packaging>=21.0
Requires-Dist: pyyaml>=6.0
Requires-Dist: requests>=2.28.0
Requires-Dist: tomli>=2.0.0; python_version < '3.11'
Provides-Extra: dev
Requires-Dist: mypy>=1.0.0; extra == 'dev'
Requires-Dist: pytest-cov>=4.0.0; extra == 'dev'
Requires-Dist: pytest>=7.0.0; extra == 'dev'
Requires-Dist: ruff>=0.1.0; extra == 'dev'
Requires-Dist: types-pyyaml>=6.0.0; extra == 'dev'
Requires-Dist: types-requests>=2.28.0; extra == 'dev'
